{
  "notice_publication_id": "325182-2024",
  "buyer": {
    "official_name": "Kildare and Wicklow Education and Training Board",
    "email": "procurement@kwetb.ie",
    "legal_type": "pub-undert-cga",
    "activity": "education",
    "address": {
      "street": "Level 5, Áras Chill Dara",
      "city": "Naas",
      "postal_code": "W91X77F",
      "country": "IRL"
    },
    "website": "https://kwetb.ie/",
    "company_id": "20083465",
    "phone": "45988000"
  },
  "procedure": {
    "title": "Invitation to Tender for Contractor Works services for accessibility works at Colaiste Bhride Carnew Co Wicklow",
    "description": "**Title: Invitation to Tender for Contractor Works Services for Accessibility Works at Colaiste Bhride Carnew, Co. Wicklow**\n\n**Description:**\nThe Kildare and Wicklow Education and Training Board (KWETB) invites bids for the provision of contractor works services to enhance accessibility at Colaiste Bhride Carnew, Co. Wicklow. The works will involve the following:\n\n1. **Provision of New Automated Doors with Access Control in Existing Glazed Screen to the Front of the Building:**\n   - The successful bidder will be responsible for installing new automated doors with access control systems to ensure seamless and secure entry for all users. This includes integrating the doors with existing security systems and ensuring compliance with current accessibility standards.\n\n2. **Minor Improvements to Existing Accessible Toilets:**\n   - The contractor will undertake minor improvements to the existing accessible toilets, including upgrading fixtures and fittings to meet modern accessibility requirements. This may include installing grab rails, improving lighting, and ensuring that all facilities are fully compliant with disability access standards.\n\n**Key Considerations:**\n- **Quality of Work:** The contractor must demonstrate a high level of expertise in accessibility works, with a proven track record of delivering similar projects.\n- **Compliance with Regulations:** The bidder must ensure that all works comply with relevant Irish and EU accessibility regulations, including the Disability Act 2005 and the European Union's Accessibility Act.\n- **Safety Measures:** The contractor must implement robust safety measures during the execution of the works to protect both staff and students.\n- **Timely Completion:** The bidder should provide a detailed project timeline and ensure that the works are completed within the specified timeframe to minimize disruption to educational activities.\n- **Maintenance and Support:** The contractor should provide a maintenance plan for the installed systems, ensuring that they remain functional and accessible over time.\n\n**Evaluation Criteria:**\n- **Technical Competence:** The bidder's experience in similar accessibility projects, including their ability to meet regulatory requirements.\n- **Quality of Proposal:** Clarity, completeness, and coherence of the proposal, including detailed methodologies and timelines.\n- **Price:** The total cost of the project, including all materials, labor, and any additional services required.\n- **Health and Safety Record:** The bidder's health and safety record, including any previous incidents or accidents related to similar projects.\n- **References:** Previous clients or projects that demonstrate the bidder's capability in delivering high-quality accessibility works.\n\nBy responding to this tender, the successful bidder will contribute to enhancing the educational environment at Colaiste Bhride Carnew, ensuring that all students and staff have equal access to facilities and services. The KWETB is committed to providing inclusive and accessible education, and this project is a critical step towards achieving this goal.",
    "identifier": "2c43ab48-0bd7-4961-89fa-b7067df177b9",
    "type": "open",
    "accelerated": "false",
    "deadline_date": "2024-06-25+01:00",
    "deadline_time": "17:00:00+01:00"
  },
  "purpose": {
    "main_nature": "works",
    "main_classification": "45214000",
    "additional_classifications": [
      "45210000",
      "45214200",
      "45210000",
      "45214200"
    ],
    "place_of_performance": ""
  },
  "value": {
    "estimated_value": "15000",
    "currency": "",
    "maximum_value": "0"
  },
  "general_information": {
    "terms_of_submission": "required",
    "variant_submissions": "",
    "electronic_invoicing": "required",
    "electronic_ordering": "false",
    "electronic_payment": "false"
  },
  "tendering_process": {
    "procedure_code": "open",
    "submission_method": "required",
    "government_agreement_constraint": "true",
    "open_tender_date": "2024-06-27+01:00",
    "open_tender_time": "00:00:00+01:00",
    "open_tender_location": "https://www.etenders.gov.ie/epps/cft/prepareViewCfTWS.do?resourceId=3618028"
  },
  "tendering_terms": {
    "variant_constraint": "",
    "funding_program": "no-eu-funds",
    "recurring_procurement": "",
    "multiple_tenders": "not-allowed",
    "esignature_submission": "",
    "ecatalog_submission": "not-allowed",
    "tender_validity_period": "",
    "tender_validity_period_unit": "",
    "security_clearance": ""
  },
  "lots": [
    {
      "lot": "LOT-0001",
      "title": "Invitation to Tender for Contractor Works services for accessibility works at Colaiste Bhride Carnew Co Wicklow",
      "description": "The works will involve the provision new 1. Automated Doors with Access Control in existing Glazed Screen to front of building and 2. Minor Improvements to existing Accessible Toilet.",
      "main_nature": "works",
      "main_classification": "45214000",
      "additional_classifications": [
        "45210000",
        "45214200"
      ],
      "place_of_performance": "",
      "country": "",
      "value": {
        "estimated_value": "15000",
        "currency": "",
        "maximum_value": "0"
      },
      "general_information": {
        "reserved_participation": "none",
        "selection_criteria": "ef-stand",
        "variant_submissions": "",
        "electronic_invoicing": "required",
        "electronic_ordering": "false",
        "electronic_payment": "false"
      },
      "specific_information": {
        "procedure_relaunch": "",
        "framework_agreement": "none",
        "dps_usage": "none",
        "reserved_execution": "not-known",
        "second_stage_indicator": ""
      }
    }
  ],
  "useful_links": [
    "https://www.etenders.gov.ie/epps/cft/listContractDocuments.do?resourceId=3618028"
  ],
  "pdf_link": "https://ted.europa.eu/en/notice/325182-2024/pdf"
}